{
  "_id": "f27e2159cc0df17f",
  "_key": "!tables!f27e2159cc0df17f",
  "name": "Village People Ruler",
  "img": "icons/svg/d20-grey.svg",
  "description": "",
  "results": [
    {
      "_id": "53ee8808a5bcace5",
      "_key": "!tables.results!f27e2159cc0df17f.53ee8808a5bcace5",
      "type": 0,
      "text": "Bandits",
      "weight": 1,
      "range": [
        1,
        1
      ],
      "drawn": false,
      "img": "icons/svg/d20-black.svg",
      "documentId": null,
      "flags": {}
    },
    {
      "_id": "69d37f265f7c0b33",
      "_key": "!tables.results!f27e2159cc0df17f.69d37f265f7c0b33",
      "type": 0,
      "text": "Council",
      "weight": 1,
      "range": [
        2,
        2
      ],
      "drawn": false,
      "img": "icons/svg/d20-black.svg",
      "documentId": null,
      "flags": {}
    },
    {
      "_id": "256055554cc98388",
      "_key": "!tables.results!f27e2159cc0df17f.256055554cc98388",
      "type": 0,
      "text": "Mayor",
      "weight": 1,
      "range": [
        3,
        3
      ],
      "drawn": false,
      "img": "icons/svg/d20-black.svg",
      "documentId": null,
      "flags": {}
    },
    {
      "_id": "f3216fada140a9f3",
      "_key": "!tables.results!f27e2159cc0df17f.f3216fada140a9f3",
      "type": 0,
      "text": "Merchant",
      "weight": 1,
      "range": [
        4,
        4
      ],
      "drawn": false,
      "img": "icons/svg/d20-black.svg",
      "documentId": null,
      "flags": {}
    },
    {
      "_id": "5f540c8e7f0e407c",
      "_key": "!tables.results!f27e2159cc0df17f.5f540c8e7f0e407c",
      "type": 0,
      "text": "Priest",
      "weight": 1,
      "range": [
        5,
        5
      ],
      "drawn": false,
      "img": "icons/svg/d20-black.svg",
      "documentId": null,
      "flags": {}
    },
    {
      "_id": "0e3dea2b56f81601",
      "_key": "!tables.results!f27e2159cc0df17f.0e3dea2b56f81601",
      "type": 0,
      "text": "Vampire/Lycanthrope",
      "weight": 1,
      "range": [
        6,
        6
      ],
      "drawn": false,
      "img": "icons/svg/d20-black.svg",
      "documentId": null,
      "flags": {}
    },
    {
      "_id": "4fe14304a37daf77",
      "_key": "!tables.results!f27e2159cc0df17f.4fe14304a37daf77",
      "type": 0,
      "text": "Village elder",
      "weight": 1,
      "range": [
        7,
        7
      ],
      "drawn": false,
      "img": "icons/svg/d20-black.svg",
      "documentId": null,
      "flags": {}
    },
    {
      "_id": "f1c25cc27a8ec25b",
      "_key": "!tables.results!f27e2159cc0df17f.f1c25cc27a8ec25b",
      "type": 0,
      "text": "Witch",
      "weight": 1,
      "range": [
        8,
        8
      ],
      "drawn": false,
      "img": "icons/svg/d20-black.svg",
      "documentId": null,
      "flags": {}
    }
  ],
  "formula": "1d8",
  "replacement": true,
  "displayRoll": true,
  "folder": "f41eb6c854728b22",
  "flags": {}
}